sorl_thumbnail_serializer/__init__.py
sorl_thumbnail_serializer/__init__.pyc
sorl_thumbnail_serializer/fields.py
sorl_thumbnail_serializer/fields.pyc
sorl_thumbnail_serializer/__pycache__/__init__.cpython-35.pyc
sorl_thumbnail_serializer_field-0.2.1.dist-info/DESCRIPTION.rst
sorl_thumbnail_serializer_field-0.2.1.dist-info/METADATA
sorl_thumbnail_serializer_field-0.2.1.dist-info/RECORD
sorl_thumbnail_serializer_field-0.2.1.dist-info/WHEEL
sorl_thumbnail_serializer_field-0.2.1.dist-info/metadata.json
sorl_thumbnail_serializer_field-0.2.1.dist-info/top_level.txt
tests/test_project/__init__.py
tests/test_project/settings.py
tests/test_project/settings_test.py
tests/test_project/urls.py
tests/test_project/wsgi.py
tests/test_project/test_app/__init__.py
tests/test_project/test_app/api.py
tests/test_project/test_app/models.py
tests/test_project/test_app/tests.py
tests/test_project/test_app/urls.py
