Metadata-Version: 1.1
Name: sorl-thumbnail-serializer-field
Version: 0.2.1
Summary: An image serializer field for use with sorl and Django REST Framework.
Home-page: https://github.com/dessibelle/sorl-thumbnail-serializer-field
Author: Simon Fransson
Author-email: simon@dessibelle.se
License: MIT License
Download-URL: https://github.com/dessibelle/sorl-thumbnail-serializer-field/archive/0.1.tar.gz
Platform: UNKNOWN
Classifier: Environment :: Web Environment
Classifier: Framework :: Django
Classifier: Intended Audience :: Developers
Classifier: License :: OSI Approved :: MIT License
Classifier: Operating System :: OS Independent
Classifier: Programming Language :: Python
Classifier: Programming Language :: Python :: 2
Classifier: Programming Language :: Python :: 2.7
Classifier: Programming Language :: Python :: 3
Classifier: Programming Language :: Python :: 3.3
Classifier: Programming Language :: Python :: 3.4
Classifier: Programming Language :: Python :: 3.5
Classifier: Topic :: Internet :: WWW/HTTP
Classifier: Topic :: Internet :: WWW/HTTP :: Dynamic Content
